aws_cdk_lambda_poetry_asset/Dockerfile
aws_cdk_lambda_poetry_asset/__init__.py
aws_cdk_lambda_poetry_asset/zip_asset_code.py
aws_cdk_lambda_poetry_asset-0.5.2.dist-info/LICENSE
aws_cdk_lambda_poetry_asset-0.5.2.dist-info/METADATA
aws_cdk_lambda_poetry_asset-0.5.2.dist-info/WHEEL
aws_cdk_lambda_poetry_asset-0.5.2.dist-info/RECORD
