Metadata-Version: 2.1
Name: aws-cdk-lambda-poetry-asset
Version: 0.5.2
Summary: AWS CDK construct for packaging lambda functions with dependencies
Home-page: https://github.com/jesse-peters/aws-cdk-lambda-poetry-asset
License: MIT
Keywords: AWS,CDK,Lambda,Construct,Poetry
Author: Jesse Peters
Author-email: jesse@resist.bot
Requires-Python: >=3.9,<4.0
Classifier: License :: OSI Approved :: MIT License
Classifier: Programming Language :: Python :: 3
Classifier: Programming Language :: Python :: 3.9
Classifier: Programming Language :: Python :: 3.10
Classifier: Programming Language :: Python :: 3.11
Requires-Dist: aws-cdk-lib (>=2.0.0,<3.0.0)
Requires-Dist: isort (>=5.12.0,<6.0.0)
Requires-Dist: python-on-whales (>=0.44.0,<0.45.0)
Requires-Dist: toml (>=0.10.2,<0.11.0)
Project-URL: Repository, https://github.com/jesse-peters/aws-cdk-lambda-poetry-asset
